openhands/tools/__init__.py
openhands/tools/py.typed
openhands/tools/apply_patch/__init__.py
openhands/tools/apply_patch/core.py
openhands/tools/apply_patch/definition.py
openhands/tools/browser_use/__init__.py
openhands/tools/browser_use/definition.py
openhands/tools/browser_use/impl.py
openhands/tools/browser_use/impl_windows.py
openhands/tools/browser_use/logging_fix.py
openhands/tools/browser_use/server.py
openhands/tools/delegate/__init__.py
openhands/tools/delegate/definition.py
openhands/tools/delegate/impl.py
openhands/tools/delegate/registration.py
openhands/tools/delegate/visualizer.py
openhands/tools/delegate/templates/delegate_tool_description.j2
openhands/tools/file_editor/__init__.py
openhands/tools/file_editor/definition.py
openhands/tools/file_editor/editor.py
openhands/tools/file_editor/exceptions.py
openhands/tools/file_editor/impl.py
openhands/tools/file_editor/utils/__init__.py
openhands/tools/file_editor/utils/config.py
openhands/tools/file_editor/utils/constants.py
openhands/tools/file_editor/utils/diff.py
openhands/tools/file_editor/utils/encoding.py
openhands/tools/file_editor/utils/file_cache.py
openhands/tools/file_editor/utils/history.py
openhands/tools/file_editor/utils/shell.py
openhands/tools/gemini/__init__.py
openhands/tools/gemini/edit/__init__.py
openhands/tools/gemini/edit/definition.py
openhands/tools/gemini/edit/impl.py
openhands/tools/gemini/list_directory/__init__.py
openhands/tools/gemini/list_directory/definition.py
openhands/tools/gemini/list_directory/impl.py
openhands/tools/gemini/read_file/__init__.py
openhands/tools/gemini/read_file/definition.py
openhands/tools/gemini/read_file/impl.py
openhands/tools/gemini/write_file/__init__.py
openhands/tools/gemini/write_file/definition.py
openhands/tools/gemini/write_file/impl.py
openhands/tools/glob/__init__.py
openhands/tools/glob/definition.py
openhands/tools/glob/impl.py
openhands/tools/grep/__init__.py
openhands/tools/grep/definition.py
openhands/tools/grep/impl.py
openhands_tools-1.10.0.dist-info/METADATA
openhands_tools-1.10.0.dist-info/WHEEL
openhands_tools-1.10.0.dist-info/top_level.txt
openhands_tools-1.10.0.dist-info/RECORD
