Metadata-Version: 2.4
Name: openhands-tools
Version: 1.10.0
Summary: OpenHands Tools - Runtime tools for AI agents
Project-URL: Source, https://github.com/OpenHands/software-agent-sdk
Project-URL: Homepage, https://github.com/OpenHands/software-agent-sdk
Project-URL: Documentation, https://docs.openhands.dev/sdk
Project-URL: Bug Tracker, https://github.com/OpenHands/software-agent-sdk/issues
Requires-Python: >=3.12
Requires-Dist: openhands-sdk
Requires-Dist: bashlex>=0.18
Requires-Dist: binaryornot>=0.4.4
Requires-Dist: cachetools
Requires-Dist: libtmux>=0.53.0
Requires-Dist: pydantic>=2.11.7
Requires-Dist: browser-use>=0.8.0
Requires-Dist: func-timeout>=4.3.5
Requires-Dist: tom-swe>=1.0.3
